LICENSE
MANIFEST.in
README.md
README.rst
setup.py
pyopening_hours/OpeningHours.py
pyopening_hours/__init__.py
pyopening_hours.egg-info/PKG-INFO
pyopening_hours.egg-info/SOURCES.txt
pyopening_hours.egg-info/dependency_links.txt
pyopening_hours.egg-info/requires.txt
pyopening_hours.egg-info/top_level.txt
pyopening_hours/node_modules/.include_empty_dir
pyopening_hours/node_modules/opening_hours
pyopening_hours/node_modules/opening_hours/LICENSE
pyopening_hours/node_modules/opening_hours/Makefile
pyopening_hours/node_modules/opening_hours/README.md
pyopening_hours/node_modules/opening_hours/benchmark.js
pyopening_hours/node_modules/opening_hours/interactive_testing.js
pyopening_hours/node_modules/opening_hours/opening_hours.js
pyopening_hours/node_modules/opening_hours/package.json
pyopening_hours/node_modules/opening_hours/real_test.js
pyopening_hours/node_modules/opening_hours/test.js
pyopening_hours/node_modules/opening_hours/node_modules/i18next/.npmignore
pyopening_hours/node_modules/opening_hours/node_modules/i18next/.travis.yml
pyopening_hours/node_modules/opening_hours/node_modules/i18next/Makefile
pyopening_hours/node_modules/opening_hours/node_modules/i18next/README.md
pyopening_hours/node_modules/opening_hours/node_modules/i18next/index.js
pyopening_hours/node_modules/opening_hours/node_modules/i18next/license
pyopening_hours/node_modules/opening_hours/node_modules/i18next/package.json
pyopening_hours/node_modules/opening_hours/node_modules/i18next/backends/couchDb/.npmignore
pyopening_hours/node_modules/opening_hours/node_modules/i18next/backends/couchDb/index.js
pyopening_hours/node_modules/opening_hours/node_modules/i18next/backends/couchDb/package.json
pyopening_hours/node_modules/opening_hours/node_modules/i18next/backends/couchDb/sync.js
pyopening_hours/node_modules/opening_hours/node_modules/i18next/backends/gettext/.npmignore
pyopening_hours/node_modules/opening_hours/node_modules/i18next/backends/gettext/index.js
pyopening_hours/node_modules/opening_hours/node_modules/i18next/backends/gettext/package.json
pyopening_hours/node_modules/opening_hours/node_modules/i18next/backends/gettext/sync.js
