Metadata-Version: 1.0
Name: pyopening-hours
Version: 0.3.0
Summary: Python module providing access to the opening_hours.js library which is written in JavaScript.
Home-page: https://github.com/ypid/pyopening_hours
Author: Robin `ypid` Schneider
Author-email: ypid23@aol.de
License: GPLv3
Keywords: OSM,OpenStreetMap,opening_hours
Platform: UNKNOWN
